odoo/addons/account_tag_menu/README.rst
odoo/addons/account_tag_menu/__init__.py
odoo/addons/account_tag_menu/__manifest__.py
odoo/addons/account_tag_menu/demo/account_tax_data.xml
odoo/addons/account_tag_menu/demo/account_tax_tags.xml
odoo/addons/account_tag_menu/i18n/account_tag_menu.pot
odoo/addons/account_tag_menu/i18n/ar.po
odoo/addons/account_tag_menu/i18n/de.po
odoo/addons/account_tag_menu/i18n/fr.po
odoo/addons/account_tag_menu/models/__init__.py
odoo/addons/account_tag_menu/models/account_tag.py
odoo/addons/account_tag_menu/static/description/icon.png
odoo/addons/account_tag_menu/views/account_tag.xml
odoo11_addon_account_tag_menu-11.0.1.0.0.99.dev15.dist-info/METADATA
odoo11_addon_account_tag_menu-11.0.1.0.0.99.dev15.dist-info/RECORD
odoo11_addon_account_tag_menu-11.0.1.0.0.99.dev15.dist-info/WHEEL
odoo11_addon_account_tag_menu-11.0.1.0.0.99.dev15.dist-info/top_level.txt
